AI4UEnv/__init__.py
AI4UEnv/envs/__init__.py
AI4UEnv/envs/env.py
ai4u/__init__.py
ai4u/agents.py
ai4u/ai4u2godot.py
ai4u/appserver.py
ai4u/controllers.py
ai4u/events.py
ai4u/onnxutils.py
ai4u/types.py
ai4u/utils.py
ai4u/workers.py
ai4u-0.5.0.dist-info/METADATA
ai4u-0.5.0.dist-info/WHEEL
ai4u-0.5.0.dist-info/top_level.txt
ai4u-0.5.0.dist-info/RECORD
