Metadata-Version: 2.2
Name: ai4u
Version: 0.5.0
Summary: AI4U connect Godot and python applications compatible with gynasium
Author: Gilzamir Gomes
Classifier: Programming Language :: Python :: 3.10
Classifier: License :: OSI Approved :: MIT License
Classifier: Operating System :: OS Independent
Requires-Python: >=3.10
Requires-Dist: numpy==1.26.4
Requires-Dist: gymnasium==0.29.1
Requires-Dist: shimmy==1.3.0
Requires-Dist: Pillow==11.3.0
Dynamic: author
Dynamic: classifier
Dynamic: description
Dynamic: description-content-type
Dynamic: requires-dist
Dynamic: requires-python
Dynamic: summary
